gitlab_registry_async_cleaner/__init__.py
gitlab_registry_async_cleaner/api_requests/__init__.py
gitlab_registry_async_cleaner/api_requests/requests.py
gitlab_registry_async_cleaner/cli/__init__.py
gitlab_registry_async_cleaner/cli/cli.py
gitlab_registry_async_cleaner/config_reader/__init__.py
gitlab_registry_async_cleaner/config_reader/config_reader.py
gitlab_registry_async_cleaner/gitlab/__init__.py
gitlab_registry_async_cleaner/gitlab/api_urls.py
gitlab_registry_async_cleaner/gitlab/image_registry_process.py
gitlab_registry_async_cleaner/logger/__init__.py
gitlab_registry_async_cleaner/logger/logger.py
gitlab_registry_async_cleaner/main.py
gitlab_registry_async_cleaner/tag_handler.py
gitlab_registry_async_cleaner-1.0.6.dist-info/METADATA
gitlab_registry_async_cleaner-1.0.6.dist-info/WHEEL
gitlab_registry_async_cleaner-1.0.6.dist-info/entry_points.txt
gitlab_registry_async_cleaner-1.0.6.dist-info/RECORD
