Metadata-Version: 2.1
Name: gitlab_registry_async_cleaner
Version: 1.0.6
Summary: Gitlab registry async cleaner
License: MIT
Author: Andrey Trusikhin
Author-email: a.trusikhin@yandex.ru
Requires-Python: >=3.10,<4.0
Classifier: Intended Audience :: Developers
Classifier: License :: OSI Approved :: MIT License
Classifier: Operating System :: OS Independent
Classifier: Programming Language :: Python :: 3
Classifier: Programming Language :: Python :: 3.10
Classifier: Programming Language :: Python :: 3.11
Classifier: Programming Language :: Python :: 3.12
Classifier: Topic :: Software Development :: Libraries :: Python Modules
Requires-Dist: asyncio (>=3.4.3,<4.0.0)
Requires-Dist: httpx (>=0.27.0,<0.28.0)
Requires-Dist: python-dotenv (>=1.0.1,<2.0.0)
Project-URL: Documentation, https://github.com/Onder7994/gitlab_async_registry_cleaner#readme
Project-URL: Homepage, https://github.com/Onder7994/gitlab_async_registry_cleaner
Project-URL: Repository, https://github.com/Onder7994/gitlab_async_registry_cleaner
